{
	"configurations" : 
	[
		{
			"directories" : 
			[
				{
					"build" : ".",
					"jsonFile" : "directory-.-Debug-f5ebdc15457944623624.json",
					"minimumCMakeVersion" : 
					{
						"string" : "3.0"
					},
					"projectIndex" : 0,
					"source" : ".",
					"targetIndexes" : 
					[
						0,
						1,
						2,
						3
					]
				}
			],
			"name" : "Debug",
			"projects" : 
			[
				{
					"directoryIndexes" : 
					[
						0
					],
					"name" : "Test",
					"targetIndexes" : 
					[
						0,
						1,
						2,
						3
					]
				}
			],
			"targets" : 
			[
				{
					"directoryIndex" : 0,
					"id" : "Test::@6890427a1f51a3e7e1df",
					"jsonFile" : "target-Test-Debug-7f01dd2bb43f94052835.json",
					"name" : "Test",
					"projectIndex" : 0
				},
				{
					"directoryIndex" : 0,
					"id" : "erase::@6890427a1f51a3e7e1df",
					"jsonFile" : "target-erase-Debug-b0e7a7def875f7d1bda1.json",
					"name" : "erase",
					"projectIndex" : 0
				},
				{
					"directoryIndex" : 0,
					"id" : "flash::@6890427a1f51a3e7e1df",
					"jsonFile" : "target-flash-Debug-60724da96734a13b8079.json",
					"name" : "flash",
					"projectIndex" : 0
				},
				{
					"directoryIndex" : 0,
					"id" : "read::@6890427a1f51a3e7e1df",
					"jsonFile" : "target-read-Debug-997c6e6d35a01b57e1bb.json",
					"name" : "read",
					"projectIndex" : 0
				}
			]
		}
	],
	"kind" : "codemodel",
	"paths" : 
	{
		"build" : "/home/t0ti20/Desktop/VS-Code/GitHub/SOCs_Drivers/STM32F103/STM32F103C8/build",
		"source" : "/home/t0ti20/Desktop/VS-Code/GitHub/SOCs_Drivers/STM32F103/STM32F103C8"
	},
	"version" : 
	{
		"major" : 2,
		"minor" : 3
	}
}
